{"positionDefinitions":[{"name":"fb853520","positions":[{"x":0.0,"y":0.0,"z":0.0},{"x":0.0,"y":0.0,"z":80.0}],"positionsFlipped":[{"x":0.0,"y":0.0,"z":0.0},{"x":0.0,"y":0.0,"z":80.0}]},{"name":"d83b317","positions":[{"x":0.0,"y":0.0,"z":0.0},{"x":0.0,"y":0.0,"z":80.0}],"positionsFlipped":[{"x":0.0,"y":0.0,"z":0.0},{"x":0.0,"y":0.0,"z":80.0}]},{"name":"2e0fb76","positions":[{"x":0.0,"y":0.0,"z":0.0},{"x":0.0,"y":0.0,"z":80.0}],"positionsFlipped":[{"x":0.0,"y":0.0,"z":0.0},{"x":0.0,"y":0.0,"z":80.0}]},{"name":"3a6ee4a4","positions":[{"x":0.0,"y":0.0,"z":40.0},{"x":0.0,"y":0.0,"z":-40.0},{"x":0.0,"y":0.0,"z":-104.0},{"x":0.0,"y":0.0,"z":120.0}],"positionsFlipped":[{"x":0.0,"y":0.0,"z":40.0},{"x":0.0,"y":0.0,"z":-40.0},{"x":0.0,"y":0.0,"z":-104.0},{"x":0.0,"y":0.0,"z":120.0}]},{"name":"2ac8013b","positions":[{"x":0.0,"y":0.0,"z":40.0},{"x":0.0,"y":0.0,"z":-40.0},{"x":0.0,"y":0.0,"z":-104.0},{"x":0.0,"y":0.0,"z":120.0}],"positionsFlipped":[{"x":0.0,"y":0.0,"z":40.0},{"x":0.0,"y":0.0,"z":-40.0},{"x":0.0,"y":0.0,"z":-104.0},{"x":0.0,"y":0.0,"z":120.0}]},{"name":"dc6286ad","positions":[{"x":0.0,"y":0.0,"z":40.0},{"x":0.0,"y":0.0,"z":-40.0},{"x":0.0,"y":0.0,"z":-104.0},{"x":0.0,"y":0.0,"z":120.0}],"positionsFlipped":[{"x":0.0,"y":0.0,"z":40.0},{"x":0.0,"y":0.0,"z":-40.0},{"x":0.0,"y":0.0,"z":-104.0},{"x":0.0,"y":0.0,"z":120.0}]},{"name":"b8f77975","positions":[{"x":0.0,"y":0.0,"z":40.0},{"x":0.0,"y":0.0,"z":-40.0},{"x":0.0,"y":0.0,"z":-104.0},{"x":0.0,"y":0.0,"z":120.0}],"positionsFlipped":[{"x":0.0,"y":0.0,"z":40.0},{"x":0.0,"y":0.0,"z":-40.0},{"x":0.0,"y":0.0,"z":-104.0},{"x":0.0,"y":0.0,"z":120.0}]},{"name":"e479af47","positions":[{"x":0.0,"y":0.0,"z":40.0},{"x":0.0,"y":0.0,"z":-40.0},{"x":0.0,"y":0.0,"z":-104.0},{"x":0.0,"y":0.0,"z":120.0}],"positionsFlipped":[{"x":0.0,"y":0.0,"z":40.0},{"x":0.0,"y":0.0,"z":-40.0},{"x":0.0,"y":0.0,"z":-104.0},{"x":0.0,"y":0.0,"z":120.0}]},{"name":"2ee61724","positions":[{"x":0.0,"y":0.0,"z":40.0},{"x":0.0,"y":0.0,"z":-40.0},{"x":0.0,"y":0.0,"z":-104.0},{"x":0.0,"y":0.0,"z":120.0}],"positionsFlipped":[{"x":0.0,"y":0.0,"z":40.0},{"x":0.0,"y":0.0,"z":-40.0},{"x":0.0,"y":0.0,"z":-104.0},{"x":0.0,"y":0.0,"z":120.0}]},{"name":"1808ee13","positions":[{"x":0.0,"y":0.0,"z":40.0},{"x":0.0,"y":0.0,"z":-40.0},{"x":0.0,"y":0.0,"z":-104.0},{"x":0.0,"y":0.0,"z":120.0}],"positionsFlipped":[{"x":0.0,"y":0.0,"z":40.0},{"x":0.0,"y":0.0,"z":-40.0},{"x":0.0,"y":0.0,"z":-104.0},{"x":0.0,"y":0.0,"z":120.0}]},{"name":"d2ab7683","positions":[{"x":0.0,"y":0.0,"z":40.0},{"x":0.0,"y":0.0,"z":-40.0},{"x":0.0,"y":0.0,"z":-104.0},{"x":0.0,"y":0.0,"z":120.0}],"positionsFlipped":[{"x":0.0,"y":0.0,"z":40.0},{"x":0.0,"y":0.0,"z":-40.0},{"x":0.0,"y":0.0,"z":-104.0},{"x":0.0,"y":0.0,"z":120.0}]},{"name":"4032bcea","positions":[{"x":0.0,"y":0.0,"z":-72.0}],"positionsFlipped":[{"x":0.0,"y":0.0,"z":-72.0}]},{"name":"cc5002ba","positions":[{"x":0.0,"y":0.0,"z":-72.0}],"positionsFlipped":[{"x":0.0,"y":0.0,"z":-72.0}]},{"name":"3f1e107b","positions":[{"x":0.0,"y":0.0,"z":-72.0}],"positionsFlipped":[{"x":0.0,"y":0.0,"z":-72.0}]},{"name":"c38f619","positions":[{"x":0.0,"y":0.0,"z":-144.0}],"positionsFlipped":[]},{"name":"6b080df3","positions":[{"x":0.0,"y":0.0,"z":-144.0}],"positionsFlipped":[]},{"name":"1d6e9444","positions":[{"x":0.0,"y":0.0,"z":-144.0}],"positionsFlipped":[]},{"name":"58e5970c","positions":[{"x":0.0,"y":0.0,"z":144.0}],"positionsFlipped":[]},{"name":"856bee10","positions":[{"x":0.0,"y":0.0,"z":144.0}],"positionsFlipped":[]},{"name":"dc3707ba","positions":[{"x":0.0,"y":0.0,"z":144.0}],"positionsFlipped":[]},{"name":"743d0dc4","positions":[{"x":0.0,"y":0.0,"z":0.0},{"x":0.0,"y":0.0,"z":80.0}],"positionsFlipped":[{"x":0.0,"y":0.0,"z":0.0},{"x":0.0,"y":0.0,"z":80.0}]},{"name":"12aca24b","positions":[{"x":0.0,"y":0.0,"z":40.0},{"x":0.0,"y":0.0,"z":-40.0},{"x":0.0,"y":0.0,"z":-104.0},{"x":0.0,"y":0.0,"z":120.0}],"positionsFlipped":[{"x":0.0,"y":0.0,"z":40.0},{"x":0.0,"y":0.0,"z":-40.0},{"x":0.0,"y":0.0,"z":-104.0},{"x":0.0,"y":0.0,"z":120.0}]},{"name":"b0eaba49","positions":[{"x":0.0,"y":0.0,"z":40.0},{"x":0.0,"y":0.0,"z":-40.0},{"x":0.0,"y":0.0,"z":-104.0},{"x":0.0,"y":0.0,"z":120.0}],"positionsFlipped":[{"x":0.0,"y":0.0,"z":40.0},{"x":0.0,"y":0.0,"z":-40.0},{"x":0.0,"y":0.0,"z":-104.0},{"x":0.0,"y":0.0,"z":120.0}]},{"name":"bf64a046","positions":[{"x":0.0,"y":0.0,"z":-72.0}],"positionsFlipped":[{"x":0.0,"y":0.0,"z":-72.0}]},{"name":"492db87b","positions":[{"x":0.0,"y":0.0,"z":-144.0}],"positionsFlipped":[]},{"name":"fbbbcaac","positions":[{"x":0.0,"y":0.0,"z":144.0}],"positionsFlipped":[]},{"name":"8454fb9c","positions":[{"x":0.0,"y":0.0,"z":-144.0}],"positionsFlipped":[]},{"name":"a9d97cf5","positions":[{"x":0.0,"y":0.0,"z":-144.0}],"positionsFlipped":[]},{"name":"fb2751a4","positions":[{"x":0.0,"y":0.0,"z":-144.0}],"positionsFlipped":[]},{"name":"2801a675","positions":[{"x":0.0,"y":0.0,"z":-144.0}],"positionsFlipped":[]},{"name":"7341dc4b","positions":[{"x":0.0,"y":0.0,"z":0.0}],"positionsFlipped":[{"x":0.0,"y":0.0,"z":0.0}]},{"name":"6060a9ba","positions":[{"x":0.0,"y":0.0,"z":0.0}],"positionsFlipped":[{"x":0.0,"y":0.0,"z":0.0}]},{"name":"e1c02d77","positions":[{"x":0.0,"y":0.0,"z":0.0}],"positionsFlipped":[{"x":0.0,"y":0.0,"z":0.0}]},{"name":"32f39c1d","positions":[{"x":0.0,"y":0.0,"z":40.0},{"x":0.0,"y":0.0,"z":-40.0},{"x":0.0,"y":0.0,"z":-104.0},{"x":0.0,"y":0.0,"z":120.0}],"positionsFlipped":[{"x":0.0,"y":0.0,"z":40.0},{"x":0.0,"y":0.0,"z":-40.0},{"x":0.0,"y":0.0,"z":-104.0},{"x":0.0,"y":0.0,"z":120.0}]},{"name":"95c68551","positions":[{"x":0.0,"y":0.0,"z":0.0}],"positionsFlipped":[{"x":0.0,"y":0.0,"z":0.0}]},{"name":"cc8d130","positions":[{"x":0.0,"y":0.0,"z":0.0}],"positionsFlipped":[{"x":0.0,"y":0.0,"z":0.0}]},{"name":"e36d3765","positions":[{"x":0.0,"y":0.0,"z":0.0}],"positionsFlipped":[]},{"name":"a40560bc","positions":[{"x":0.0,"y":0.0,"z":40.0},{"x":0.0,"y":0.0,"z":-40.0},{"x":0.0,"y":0.0,"z":-104.0},{"x":0.0,"y":0.0,"z":120.0}],"positionsFlipped":[{"x":0.0,"y":0.0,"z":40.0},{"x":0.0,"y":0.0,"z":-40.0},{"x":0.0,"y":0.0,"z":-104.0},{"x":0.0,"y":0.0,"z":120.0}]}]}