{"vehicles":[{"id":"mtr_custom_train_e2330_head","name":"E233 Chuo Line TC Front","color":"FF6600","transportMode":"TRAIN","length":20.0,"width":2.0,"bogie1Position":-6.8,"bogie2Position":6.8,"couplingPadding1":0.0,"couplingPadding2":0.0,"description":"Trailer Cab","wikipediaArticle":"E233_series","tags":[],"models":[{"modelResource":"mtr:e233/e233.bbmodel","textureResource":"mtr:e233/e233-0.png","modelPropertiesResource":"mtr:properties_53773b80.json","positionDefinitionsResource":"mtr:definition_1b8ce00c.json","flipTextureV":true}],"bogie1Models":[{"modelResource":"mtr:e233/e233.bbmodel","textureResource":"mtr:e233/e233-0.png","modelPropertiesResource":"mtr:properties_25031441.json","positionDefinitionsResource":"mtr:definition_18aa71c7.json","flipTextureV":true}],"bogie2Models":[{"modelResource":"mtr:e233/e233.bbmodel","textureResource":"mtr:e233/e233-0.png","modelPropertiesResource":"mtr:properties_cacce504.json","positionDefinitionsResource":"mtr:definition_b3190b9e.json","flipTextureV":true}],"hasGangway1":false,"hasGangway2":true,"hasBarrier1":false,"hasBarrier2":false,"legacyRiderOffset":0.0,"bveSoundBaseResource":"e233","legacySpeedSoundBaseResource":"","legacySpeedSoundCount":1,"legacyUseAccelerationSoundsWhenCoasting":false,"legacyConstantPlaybackSpeed":false,"legacyDoorSoundBaseResource":"","legacyDoorCloseSoundTime":0.0},{"id":"mtr_custom_train_e2330_trailer","name":"E233 Series Chuo Line T","color":"FF6600","transportMode":"TRAIN","length":20.0,"width":2.0,"bogie1Position":-6.8,"bogie2Position":6.8,"couplingPadding1":0.0,"couplingPadding2":0.0,"description":"Trailer Cab","wikipediaArticle":"E233_series","tags":[],"models":[{"modelResource":"mtr:e233/e233.bbmodel","textureResource":"mtr:e233/e233-0.png","modelPropertiesResource":"mtr:properties_9e94bd1a.json","positionDefinitionsResource":"mtr:definition_500720ab.json","flipTextureV":true}],"bogie1Models":[{"modelResource":"mtr:e233/e233.bbmodel","textureResource":"mtr:e233/e233-0.png","modelPropertiesResource":"mtr:properties_e36034c.json","positionDefinitionsResource":"mtr:definition_93f3e0f6.json","flipTextureV":true}],"bogie2Models":[{"modelResource":"mtr:e233/e233.bbmodel","textureResource":"mtr:e233/e233-0.png","modelPropertiesResource":"mtr:properties_a8ea4831.json","positionDefinitionsResource":"mtr:definition_c7f62762.json","flipTextureV":true}],"hasGangway1":true,"hasGangway2":true,"hasBarrier1":false,"hasBarrier2":false,"legacyRiderOffset":0.0,"bveSoundBaseResource":"e233","legacySpeedSoundBaseResource":"","legacySpeedSoundCount":1,"legacyUseAccelerationSoundsWhenCoasting":false,"legacyConstantPlaybackSpeed":false,"legacyDoorSoundBaseResource":"","legacyDoorCloseSoundTime":0.0},{"id":"mtr_custom_train_e2330_pantograph_trailer","name":"E233 Series Chuo Line M'","color":"FF6600","transportMode":"TRAIN","length":20.0,"width":2.0,"bogie1Position":-6.8,"bogie2Position":6.8,"couplingPadding1":0.0,"couplingPadding2":0.0,"description":"Double Pantograph Motor Trailer","wikipediaArticle":"E233_series","tags":[],"models":[{"modelResource":"mtr:e233/e233.bbmodel","textureResource":"mtr:e233/e233-0.png","modelPropertiesResource":"mtr:properties_f5cc7e38.json","positionDefinitionsResource":"mtr:definition_1389b3de.json","flipTextureV":true}],"bogie1Models":[{"modelResource":"mtr:e233/e233.bbmodel","textureResource":"mtr:e233/e233-0.png","modelPropertiesResource":"mtr:properties_e49a3ab2.json","positionDefinitionsResource":"mtr:definition_6fadee71.json","flipTextureV":true}],"bogie2Models":[{"modelResource":"mtr:e233/e233.bbmodel","textureResource":"mtr:e233/e233-0.png","modelPropertiesResource":"mtr:properties_e9ca2f3c.json","positionDefinitionsResource":"mtr:definition_bfd3844b.json","flipTextureV":true}],"hasGangway1":true,"hasGangway2":true,"hasBarrier1":false,"hasBarrier2":false,"legacyRiderOffset":0.0,"bveSoundBaseResource":"e233","legacySpeedSoundBaseResource":"","legacySpeedSoundCount":1,"legacyUseAccelerationSoundsWhenCoasting":false,"legacyConstantPlaybackSpeed":false,"legacyDoorSoundBaseResource":"","legacyDoorCloseSoundTime":0.0},{"id":"mtr_custom_train_e2330_head_bqck","name":"E233 Series Chuo Line TC Back","color":"FF6600","transportMode":"TRAIN","length":20.0,"width":2.0,"bogie1Position":-6.8,"bogie2Position":6.8,"couplingPadding1":0.0,"couplingPadding2":0.0,"description":"Trailer Cab","wikipediaArticle":"E233_series","tags":[],"models":[{"modelResource":"mtr:e233/e233.bbmodel","textureResource":"mtr:e233/e233-0.png","modelPropertiesResource":"mtr:properties_66a32124.json","positionDefinitionsResource":"mtr:definition_59467f94.json","flipTextureV":true}],"bogie1Models":[{"modelResource":"mtr:e233/e233.bbmodel","textureResource":"mtr:e233/e233-0.png","modelPropertiesResource":"mtr:properties_25031441.json","positionDefinitionsResource":"mtr:definition_18aa71c7.json","flipTextureV":true}],"bogie2Models":[{"modelResource":"mtr:e233/e233.bbmodel","textureResource":"mtr:e233/e233-0.png","modelPropertiesResource":"mtr:properties_cacce504.json","positionDefinitionsResource":"mtr:definition_b3190b9e.json","flipTextureV":true}],"hasGangway1":true,"hasGangway2":false,"hasBarrier1":false,"hasBarrier2":false,"legacyRiderOffset":0.0,"bveSoundBaseResource":"e233","legacySpeedSoundBaseResource":"","legacySpeedSoundCount":1,"legacyUseAccelerationSoundsWhenCoasting":false,"legacyConstantPlaybackSpeed":false,"legacyDoorSoundBaseResource":"","legacyDoorCloseSoundTime":0.0},{"id":"mtr_custom_train_e2331_head","name":"E233-1000 Keihin-Tohoku Line TC Front","color":"0096E0","transportMode":"TRAIN","length":20.0,"width":2.0,"bogie1Position":-6.8,"bogie2Position":6.8,"couplingPadding1":0.0,"couplingPadding2":0.0,"description":"Trailer Cab","wikipediaArticle":"E233_series","tags":[],"models":[{"modelResource":"mtr:e233/e233.bbmodel","textureResource":"mtr:e233/e233-1000.png","modelPropertiesResource":"mtr:properties_eac8e6e0.json","positionDefinitionsResource":"mtr:definition_5b8d2f5.json","flipTextureV":true}],"bogie1Models":[{"modelResource":"mtr:e233/e233.bbmodel","textureResource":"mtr:e233/e233-0.png","modelPropertiesResource":"mtr:properties_e8bd2887.json","positionDefinitionsResource":"mtr:definition_d173d782.json","flipTextureV":true}],"bogie2Models":[{"modelResource":"mtr:e233/e233.bbmodel","textureResource":"mtr:e233/e233-0.png","modelPropertiesResource":"mtr:properties_b2013c48.json","positionDefinitionsResource":"mtr:definition_374dccfc.json","flipTextureV":true}],"hasGangway1":false,"hasGangway2":true,"hasBarrier1":false,"hasBarrier2":false,"legacyRiderOffset":0.0,"bveSoundBaseResource":"e233","legacySpeedSoundBaseResource":"","legacySpeedSoundCount":1,"legacyUseAccelerationSoundsWhenCoasting":false,"legacyConstantPlaybackSpeed":false,"legacyDoorSoundBaseResource":"","legacyDoorCloseSoundTime":0.0},{"id":"mtr_custom_train_e2331_trailer","name":"E233-1000 Keihin-Tohoku Line T","color":"0096E0","transportMode":"TRAIN","length":20.0,"width":2.0,"bogie1Position":-6.8,"bogie2Position":6.8,"couplingPadding1":0.0,"couplingPadding2":0.0,"description":"Trailer Cab","wikipediaArticle":"E233_series","tags":[],"models":[{"modelResource":"mtr:e233/e233.bbmodel","textureResource":"mtr:e233/e233-1000.png","modelPropertiesResource":"mtr:properties_7d73e76f.json","positionDefinitionsResource":"mtr:definition_b71e1be.json","flipTextureV":true}],"bogie1Models":[{"modelResource":"mtr:e233/e233.bbmodel","textureResource":"mtr:e233/e233-0.png","modelPropertiesResource":"mtr:properties_9d3ddbfb.json","positionDefinitionsResource":"mtr:definition_26f2c742.json","flipTextureV":true}],"bogie2Models":[{"modelResource":"mtr:e233/e233.bbmodel","textureResource":"mtr:e233/e233-0.png","modelPropertiesResource":"mtr:properties_89d6e308.json","positionDefinitionsResource":"mtr:definition_1c28773c.json","flipTextureV":true}],"hasGangway1":true,"hasGangway2":true,"hasBarrier1":false,"hasBarrier2":false,"legacyRiderOffset":0.0,"bveSoundBaseResource":"e233","legacySpeedSoundBaseResource":"","legacySpeedSoundCount":1,"legacyUseAccelerationSoundsWhenCoasting":false,"legacyConstantPlaybackSpeed":false,"legacyDoorSoundBaseResource":"","legacyDoorCloseSoundTime":0.0},{"id":"mtr_custom_train_e2331_pantograph_trailer","name":"E233-1000 Keihin-Tohoku Line M'","color":"0096E0","transportMode":"TRAIN","length":20.0,"width":2.0,"bogie1Position":-6.8,"bogie2Position":6.8,"couplingPadding1":0.0,"couplingPadding2":0.0,"description":"Double Pantograph Motor Trailer","wikipediaArticle":"E233_series","tags":[],"models":[{"modelResource":"mtr:e233/e233.bbmodel","textureResource":"mtr:e233/e233-1000.png","modelPropertiesResource":"mtr:properties_7203cd9f.json","positionDefinitionsResource":"mtr:definition_7d117271.json","flipTextureV":true}],"bogie1Models":[{"modelResource":"mtr:e233/e233.bbmodel","textureResource":"mtr:e233/e233-0.png","modelPropertiesResource":"mtr:properties_364cef26.json","positionDefinitionsResource":"mtr:definition_75641ba6.json","flipTextureV":true}],"bogie2Models":[{"modelResource":"mtr:e233/e233.bbmodel","textureResource":"mtr:e233/e233-0.png","modelPropertiesResource":"mtr:properties_baeb2ecc.json","positionDefinitionsResource":"mtr:definition_7fc601de.json","flipTextureV":true}],"hasGangway1":true,"hasGangway2":true,"hasBarrier1":false,"hasBarrier2":false,"legacyRiderOffset":0.0,"bveSoundBaseResource":"e233","legacySpeedSoundBaseResource":"","legacySpeedSoundCount":1,"legacyUseAccelerationSoundsWhenCoasting":false,"legacyConstantPlaybackSpeed":false,"legacyDoorSoundBaseResource":"","legacyDoorCloseSoundTime":0.0},{"id":"mtr_custom_train_e2331_head_bqck","name":"E233-1000 Keihin-Tohoku Line TC Back","color":"0096E0","transportMode":"TRAIN","length":20.0,"width":2.0,"bogie1Position":-6.8,"bogie2Position":6.8,"couplingPadding1":0.0,"couplingPadding2":0.0,"description":"Trailer Cab","wikipediaArticle":"E233_series","tags":[],"models":[{"modelResource":"mtr:e233/e233.bbmodel","textureResource":"mtr:e233/e233-1000.png","modelPropertiesResource":"mtr:properties_a9f645b6.json","positionDefinitionsResource":"mtr:definition_ebdaff1c.json","flipTextureV":true}],"bogie1Models":[{"modelResource":"mtr:e233/e233.bbmodel","textureResource":"mtr:e233/e233-0.png","modelPropertiesResource":"mtr:properties_e8bd2887.json","positionDefinitionsResource":"mtr:definition_d173d782.json","flipTextureV":true}],"bogie2Models":[{"modelResource":"mtr:e233/e233.bbmodel","textureResource":"mtr:e233/e233-0.png","modelPropertiesResource":"mtr:properties_b2013c48.json","positionDefinitionsResource":"mtr:definition_374dccfc.json","flipTextureV":true}],"hasGangway1":true,"hasGangway2":false,"hasBarrier1":false,"hasBarrier2":false,"legacyRiderOffset":0.0,"bveSoundBaseResource":"e233","legacySpeedSoundBaseResource":"","legacySpeedSoundCount":1,"legacyUseAccelerationSoundsWhenCoasting":false,"legacyConstantPlaybackSpeed":false,"legacyDoorSoundBaseResource":"","legacyDoorCloseSoundTime":0.0},{"id":"mtr_custom_train_e2333_head","name":"E233-3000 Tokaido Line TC Front","color":"00C728","transportMode":"TRAIN","length":20.0,"width":2.0,"bogie1Position":-6.8,"bogie2Position":6.8,"couplingPadding1":0.0,"couplingPadding2":0.0,"description":"Trailer Cab","wikipediaArticle":"E233_series","tags":[],"models":[{"modelResource":"mtr:e233/e233.bbmodel","textureResource":"mtr:e233/e233-3000.png","modelPropertiesResource":"mtr:properties_5504fd56.json","positionDefinitionsResource":"mtr:definition_160dc821.json","flipTextureV":true}],"bogie1Models":[{"modelResource":"mtr:e233/e233.bbmodel","textureResource":"mtr:e233/e233-3000.png","modelPropertiesResource":"mtr:properties_c93ad5e7.json","positionDefinitionsResource":"mtr:definition_ec8a63b2.json","flipTextureV":true}],"bogie2Models":[{"modelResource":"mtr:e233/e233.bbmodel","textureResource":"mtr:e233/e233-0.png","modelPropertiesResource":"mtr:properties_5b02f8af.json","positionDefinitionsResource":"mtr:definition_8ca18096.json","flipTextureV":true}],"hasGangway1":false,"hasGangway2":true,"hasBarrier1":false,"hasBarrier2":false,"legacyRiderOffset":0.0,"bveSoundBaseResource":"e531","legacySpeedSoundBaseResource":"","legacySpeedSoundCount":1,"legacyUseAccelerationSoundsWhenCoasting":false,"legacyConstantPlaybackSpeed":false,"legacyDoorSoundBaseResource":"","legacyDoorCloseSoundTime":0.0},{"id":"mtr_custom_train_e2333_trailer","name":"E233-3000 Tokaido Line T","color":"00C728","transportMode":"TRAIN","length":20.0,"width":2.0,"bogie1Position":-6.8,"bogie2Position":6.8,"couplingPadding1":0.0,"couplingPadding2":0.0,"description":"Trailer Cab","wikipediaArticle":"E233_series","tags":[],"models":[{"modelResource":"mtr:e233/e233.bbmodel","textureResource":"mtr:e233/e233-3000.png","modelPropertiesResource":"mtr:properties_3bd8551c.json","positionDefinitionsResource":"mtr:definition_32d07d83.json","flipTextureV":true}],"bogie1Models":[{"modelResource":"mtr:e233/e233.bbmodel","textureResource":"mtr:e233/e233-0.png","modelPropertiesResource":"mtr:properties_bf99687e.json","positionDefinitionsResource":"mtr:definition_713a33f4.json","flipTextureV":true}],"bogie2Models":[{"modelResource":"mtr:e233/e233.bbmodel","textureResource":"mtr:e233/e233-0.png","modelPropertiesResource":"mtr:properties_1b03f9fe.json","positionDefinitionsResource":"mtr:definition_498bbcbb.json","flipTextureV":true}],"hasGangway1":true,"hasGangway2":true,"hasBarrier1":false,"hasBarrier2":false,"legacyRiderOffset":0.0,"bveSoundBaseResource":"e531","legacySpeedSoundBaseResource":"","legacySpeedSoundCount":1,"legacyUseAccelerationSoundsWhenCoasting":false,"legacyConstantPlaybackSpeed":false,"legacyDoorSoundBaseResource":"","legacyDoorCloseSoundTime":0.0},{"id":"mtr_custom_train_e2333_pantograph_trailer","name":"E233-3000 Tokaido Line M'","color":"00C728","transportMode":"TRAIN","length":20.0,"width":2.0,"bogie1Position":-6.8,"bogie2Position":6.8,"couplingPadding1":0.0,"couplingPadding2":0.0,"description":"Double Pantograph Motor Trailer","wikipediaArticle":"E233_series","tags":[],"models":[{"modelResource":"mtr:e233/e233.bbmodel","textureResource":"mtr:e233/e233-3000.png","modelPropertiesResource":"mtr:properties_7c630453.json","positionDefinitionsResource":"mtr:definition_4c9a0590.json","flipTextureV":true}],"bogie1Models":[{"modelResource":"mtr:e233/e233.bbmodel","textureResource":"mtr:e233/e233-0.png","modelPropertiesResource":"mtr:properties_4f917ecd.json","positionDefinitionsResource":"mtr:definition_9aba743e.json","flipTextureV":true}],"bogie2Models":[{"modelResource":"mtr:e233/e233.bbmodel","textureResource":"mtr:e233/e233-0.png","modelPropertiesResource":"mtr:properties_eadae75.json","positionDefinitionsResource":"mtr:definition_ff0c1a4.json","flipTextureV":true}],"hasGangway1":true,"hasGangway2":true,"hasBarrier1":false,"hasBarrier2":false,"legacyRiderOffset":0.0,"bveSoundBaseResource":"e531","legacySpeedSoundBaseResource":"","legacySpeedSoundCount":1,"legacyUseAccelerationSoundsWhenCoasting":false,"legacyConstantPlaybackSpeed":false,"legacyDoorSoundBaseResource":"","legacyDoorCloseSoundTime":0.0},{"id":"mtr_custom_train_e2333_head_bqck","name":"E233-3000 Tokaido Line TC Back","color":"00C728","transportMode":"TRAIN","length":20.0,"width":2.0,"bogie1Position":-6.8,"bogie2Position":6.8,"couplingPadding1":0.0,"couplingPadding2":0.0,"description":"Trailer Cab","wikipediaArticle":"E233_series","tags":[],"models":[{"modelResource":"mtr:e233/e233.bbmodel","textureResource":"mtr:e233/e233-3000.png","modelPropertiesResource":"mtr:properties_514aff1e.json","positionDefinitionsResource":"mtr:definition_121abb0e.json","flipTextureV":true}],"bogie1Models":[{"modelResource":"mtr:e233/e233.bbmodel","textureResource":"mtr:e233/e233-3000.png","modelPropertiesResource":"mtr:properties_c93ad5e7.json","positionDefinitionsResource":"mtr:definition_ec8a63b2.json","flipTextureV":true}],"bogie2Models":[{"modelResource":"mtr:e233/e233.bbmodel","textureResource":"mtr:e233/e233-0.png","modelPropertiesResource":"mtr:properties_5b02f8af.json","positionDefinitionsResource":"mtr:definition_8ca18096.json","flipTextureV":true}],"hasGangway1":true,"hasGangway2":false,"hasBarrier1":false,"hasBarrier2":false,"legacyRiderOffset":0.0,"bveSoundBaseResource":"e531","legacySpeedSoundBaseResource":"","legacySpeedSoundCount":1,"legacyUseAccelerationSoundsWhenCoasting":false,"legacyConstantPlaybackSpeed":false,"legacyDoorSoundBaseResource":"","legacyDoorCloseSoundTime":0.0},{"id":"mtr_custom_train_e2335_head","name":"E233-5000 Keiyo Line TC Front","color":"E00000","transportMode":"TRAIN","length":20.0,"width":2.0,"bogie1Position":-6.8,"bogie2Position":6.8,"couplingPadding1":0.0,"couplingPadding2":0.0,"description":"Trailer Cab","wikipediaArticle":"E233_series","tags":[],"models":[{"modelResource":"mtr:e233/e233.bbmodel","textureResource":"mtr:e233/e233-5000.png","modelPropertiesResource":"mtr:properties_5a1d71f3.json","positionDefinitionsResource":"mtr:definition_67a4a9fd.json","flipTextureV":true}],"bogie1Models":[{"modelResource":"mtr:e233/e233.bbmodel","textureResource":"mtr:e233/e233-0.png","modelPropertiesResource":"mtr:properties_225a5a6a.json","positionDefinitionsResource":"mtr:definition_bf2e942a.json","flipTextureV":true}],"bogie2Models":[{"modelResource":"mtr:e233/e233.bbmodel","textureResource":"mtr:e233/e233-0.png","modelPropertiesResource":"mtr:properties_b1fc9363.json","positionDefinitionsResource":"mtr:definition_e414ecda.json","flipTextureV":true}],"hasGangway1":false,"hasGangway2":true,"hasBarrier1":false,"hasBarrier2":false,"legacyRiderOffset":0.0,"bveSoundBaseResource":"e233","legacySpeedSoundBaseResource":"","legacySpeedSoundCount":1,"legacyUseAccelerationSoundsWhenCoasting":false,"legacyConstantPlaybackSpeed":false,"legacyDoorSoundBaseResource":"","legacyDoorCloseSoundTime":0.0},{"id":"mtr_custom_train_e2335_trailer","name":"E233-5000 Keiyo Line T","color":"E00000","transportMode":"TRAIN","length":20.0,"width":2.0,"bogie1Position":-6.8,"bogie2Position":6.8,"couplingPadding1":0.0,"couplingPadding2":0.0,"description":"Trailer Cab","wikipediaArticle":"E233_series","tags":[],"models":[{"modelResource":"mtr:e233/e233.bbmodel","textureResource":"mtr:e233/e233-5000.png","modelPropertiesResource":"mtr:properties_225402fa.json","positionDefinitionsResource":"mtr:definition_fe60733d.json","flipTextureV":true}],"bogie1Models":[{"modelResource":"mtr:e233/e233.bbmodel","textureResource":"mtr:e233/e233-0.png","modelPropertiesResource":"mtr:properties_c2b520c1.json","positionDefinitionsResource":"mtr:definition_ae8a450d.json","flipTextureV":true}],"bogie2Models":[{"modelResource":"mtr:e233/e233.bbmodel","textureResource":"mtr:e233/e233-0.png","modelPropertiesResource":"mtr:properties_c38d7863.json","positionDefinitionsResource":"mtr:definition_28754ebc.json","flipTextureV":true}],"hasGangway1":true,"hasGangway2":true,"hasBarrier1":false,"hasBarrier2":false,"legacyRiderOffset":0.0,"bveSoundBaseResource":"e233","legacySpeedSoundBaseResource":"","legacySpeedSoundCount":1,"legacyUseAccelerationSoundsWhenCoasting":false,"legacyConstantPlaybackSpeed":false,"legacyDoorSoundBaseResource":"","legacyDoorCloseSoundTime":0.0},{"id":"mtr_custom_train_e2335_pantograph_trailer","name":"E233-5000 Keiyo Line M'","color":"E00000","transportMode":"TRAIN","length":20.0,"width":2.0,"bogie1Position":-6.8,"bogie2Position":6.8,"couplingPadding1":0.0,"couplingPadding2":0.0,"description":"Double Pantograph Motor Trailer","wikipediaArticle":"E233_series","tags":[],"models":[{"modelResource":"mtr:e233/e233.bbmodel","textureResource":"mtr:e233/e233-5000.png","modelPropertiesResource":"mtr:properties_4ab18459.json","positionDefinitionsResource":"mtr:definition_df6120b0.json","flipTextureV":true}],"bogie1Models":[{"modelResource":"mtr:e233/e233.bbmodel","textureResource":"mtr:e233/e233-0.png","modelPropertiesResource":"mtr:properties_9fc9e04b.json","positionDefinitionsResource":"mtr:definition_7d78fe94.json","flipTextureV":true}],"bogie2Models":[{"modelResource":"mtr:e233/e233.bbmodel","textureResource":"mtr:e233/e233-0.png","modelPropertiesResource":"mtr:properties_ae2241aa.json","positionDefinitionsResource":"mtr:definition_bee39d94.json","flipTextureV":true}],"hasGangway1":true,"hasGangway2":true,"hasBarrier1":false,"hasBarrier2":false,"legacyRiderOffset":0.0,"bveSoundBaseResource":"e233","legacySpeedSoundBaseResource":"","legacySpeedSoundCount":1,"legacyUseAccelerationSoundsWhenCoasting":false,"legacyConstantPlaybackSpeed":false,"legacyDoorSoundBaseResource":"","legacyDoorCloseSoundTime":0.0},{"id":"mtr_custom_train_e2335_head_bqck","name":"E233-5000 Keiyo Line TC Back","color":"E00000","transportMode":"TRAIN","length":20.0,"width":2.0,"bogie1Position":-6.8,"bogie2Position":6.8,"couplingPadding1":0.0,"couplingPadding2":0.0,"description":"Trailer Cab","wikipediaArticle":"E233_series","tags":[],"models":[{"modelResource":"mtr:e233/e233.bbmodel","textureResource":"mtr:e233/e233-5000.png","modelPropertiesResource":"mtr:properties_8c4a088c.json","positionDefinitionsResource":"mtr:definition_ee06ec1c.json","flipTextureV":true}],"bogie1Models":[{"modelResource":"mtr:e233/e233.bbmodel","textureResource":"mtr:e233/e233-0.png","modelPropertiesResource":"mtr:properties_225a5a6a.json","positionDefinitionsResource":"mtr:definition_bf2e942a.json","flipTextureV":true}],"bogie2Models":[{"modelResource":"mtr:e233/e233.bbmodel","textureResource":"mtr:e233/e233-0.png","modelPropertiesResource":"mtr:properties_b1fc9363.json","positionDefinitionsResource":"mtr:definition_e414ecda.json","flipTextureV":true}],"hasGangway1":true,"hasGangway2":false,"hasBarrier1":false,"hasBarrier2":false,"legacyRiderOffset":0.0,"bveSoundBaseResource":"e233","legacySpeedSoundBaseResource":"","legacySpeedSoundCount":1,"legacyUseAccelerationSoundsWhenCoasting":false,"legacyConstantPlaybackSpeed":false,"legacyDoorSoundBaseResource":"","legacyDoorCloseSoundTime":0.0},{"id":"mtr_custom_train_e2336_head","name":"E233-6000 Yokohama Line TC Front","color":"85D643","transportMode":"TRAIN","length":20.0,"width":2.0,"bogie1Position":-6.8,"bogie2Position":6.8,"couplingPadding1":0.0,"couplingPadding2":0.0,"description":"Trailer Cab","wikipediaArticle":"E233_series","tags":[],"models":[{"modelResource":"mtr:e233/e233.bbmodel","textureResource":"mtr:e233/e233-6000.png","modelPropertiesResource":"mtr:properties_d98606c2.json","positionDefinitionsResource":"mtr:definition_88cb25a0.json","flipTextureV":true}],"bogie1Models":[{"modelResource":"mtr:e233/e233.bbmodel","textureResource":"mtr:e233/e233-0.png","modelPropertiesResource":"mtr:properties_f6f5aea9.json","positionDefinitionsResource":"mtr:definition_83aae765.json","flipTextureV":true}],"bogie2Models":[{"modelResource":"mtr:e233/e233.bbmodel","textureResource":"mtr:e233/e233-0.png","modelPropertiesResource":"mtr:properties_2d0ec572.json","positionDefinitionsResource":"mtr:definition_ae9e690.json","flipTextureV":true}],"hasGangway1":false,"hasGangway2":true,"hasBarrier1":false,"hasBarrier2":false,"legacyRiderOffset":0.0,"bveSoundBaseResource":"e233","legacySpeedSoundBaseResource":"","legacySpeedSoundCount":1,"legacyUseAccelerationSoundsWhenCoasting":false,"legacyConstantPlaybackSpeed":false,"legacyDoorSoundBaseResource":"","legacyDoorCloseSoundTime":0.0},{"id":"mtr_custom_train_e2336_trailer","name":"E233-6000 Yokohama Line T","color":"85D643","transportMode":"TRAIN","length":20.0,"width":2.0,"bogie1Position":-6.8,"bogie2Position":6.8,"couplingPadding1":0.0,"couplingPadding2":0.0,"description":"Trailer Cab","wikipediaArticle":"E233_series","tags":[],"models":[{"modelResource":"mtr:e233/e233.bbmodel","textureResource":"mtr:e233/e233-6000.png","modelPropertiesResource":"mtr:properties_2c93d8ae.json","positionDefinitionsResource":"mtr:definition_f3aa9b00.json","flipTextureV":true}],"bogie1Models":[{"modelResource":"mtr:e233/e233.bbmodel","textureResource":"mtr:e233/e233-0.png","modelPropertiesResource":"mtr:properties_4e746beb.json","positionDefinitionsResource":"mtr:definition_ef72ebb5.json","flipTextureV":true}],"bogie2Models":[{"modelResource":"mtr:e233/e233.bbmodel","textureResource":"mtr:e233/e233-0.png","modelPropertiesResource":"mtr:properties_e4416a52.json","positionDefinitionsResource":"mtr:definition_f768af34.json","flipTextureV":true}],"hasGangway1":true,"hasGangway2":true,"hasBarrier1":false,"hasBarrier2":false,"legacyRiderOffset":0.0,"bveSoundBaseResource":"e233","legacySpeedSoundBaseResource":"","legacySpeedSoundCount":1,"legacyUseAccelerationSoundsWhenCoasting":false,"legacyConstantPlaybackSpeed":false,"legacyDoorSoundBaseResource":"","legacyDoorCloseSoundTime":0.0},{"id":"mtr_custom_train_e2336_pantograph_trailer","name":"E233-6000 Yokohama Line M'","color":"85D643","transportMode":"TRAIN","length":20.0,"width":2.0,"bogie1Position":-6.8,"bogie2Position":6.8,"couplingPadding1":0.0,"couplingPadding2":0.0,"description":"Double Pantograph Motor Trailer","wikipediaArticle":"E233_series","tags":[],"models":[{"modelResource":"mtr:e233/e233.bbmodel","textureResource":"mtr:e233/e233-6000.png","modelPropertiesResource":"mtr:properties_ede6b577.json","positionDefinitionsResource":"mtr:definition_235f537b.json","flipTextureV":true}],"bogie1Models":[{"modelResource":"mtr:e233/e233.bbmodel","textureResource":"mtr:e233/e233-0.png","modelPropertiesResource":"mtr:properties_896497df.json","positionDefinitionsResource":"mtr:definition_b660a0d0.json","flipTextureV":true}],"bogie2Models":[{"modelResource":"mtr:e233/e233.bbmodel","textureResource":"mtr:e233/e233-0.png","modelPropertiesResource":"mtr:properties_bfe65ce6.json","positionDefinitionsResource":"mtr:definition_45d56232.json","flipTextureV":true}],"hasGangway1":true,"hasGangway2":true,"hasBarrier1":false,"hasBarrier2":false,"legacyRiderOffset":0.0,"bveSoundBaseResource":"e233","legacySpeedSoundBaseResource":"","legacySpeedSoundCount":1,"legacyUseAccelerationSoundsWhenCoasting":false,"legacyConstantPlaybackSpeed":false,"legacyDoorSoundBaseResource":"","legacyDoorCloseSoundTime":0.0},{"id":"mtr_custom_train_e2336_head_bqck","name":"E233-6000 Yokohama Line TC Back","color":"85D643","transportMode":"TRAIN","length":20.0,"width":2.0,"bogie1Position":-6.8,"bogie2Position":6.8,"couplingPadding1":0.0,"couplingPadding2":0.0,"description":"Trailer Cab","wikipediaArticle":"E233_series","tags":[],"models":[{"modelResource":"mtr:e233/e233.bbmodel","textureResource":"mtr:e233/e233-6000.png","modelPropertiesResource":"mtr:properties_8af956e.json","positionDefinitionsResource":"mtr:definition_7d5d371a.json","flipTextureV":true}],"bogie1Models":[{"modelResource":"mtr:e233/e233.bbmodel","textureResource":"mtr:e233/e233-0.png","modelPropertiesResource":"mtr:properties_f6f5aea9.json","positionDefinitionsResource":"mtr:definition_83aae765.json","flipTextureV":true}],"bogie2Models":[{"modelResource":"mtr:e233/e233.bbmodel","textureResource":"mtr:e233/e233-0.png","modelPropertiesResource":"mtr:properties_2d0ec572.json","positionDefinitionsResource":"mtr:definition_ae9e690.json","flipTextureV":true}],"hasGangway1":true,"hasGangway2":false,"hasBarrier1":false,"hasBarrier2":false,"legacyRiderOffset":0.0,"bveSoundBaseResource":"e233","legacySpeedSoundBaseResource":"","legacySpeedSoundCount":1,"legacyUseAccelerationSoundsWhenCoasting":false,"legacyConstantPlaybackSpeed":false,"legacyDoorSoundBaseResource":"","legacyDoorCloseSoundTime":0.0},{"id":"mtr_custom_train_e2337_head","name":"E233-7000 Saikyo Line TC Front","color":"2A8C56","transportMode":"TRAIN","length":20.0,"width":2.0,"bogie1Position":-6.8,"bogie2Position":6.8,"couplingPadding1":0.0,"couplingPadding2":0.0,"description":"Trailer Cab","wikipediaArticle":"E233_series","tags":[],"models":[{"modelResource":"mtr:e233/e233.bbmodel","textureResource":"mtr:e233/e233-7000.png","modelPropertiesResource":"mtr:properties_24043d9a.json","positionDefinitionsResource":"mtr:definition_b2e4c930.json","flipTextureV":true}],"bogie1Models":[{"modelResource":"mtr:e233/e233.bbmodel","textureResource":"mtr:e233/e233-0.png","modelPropertiesResource":"mtr:properties_d9303360.json","positionDefinitionsResource":"mtr:definition_ad1bae01.json","flipTextureV":true}],"bogie2Models":[{"modelResource":"mtr:e233/e233.bbmodel","textureResource":"mtr:e233/e233-0.png","modelPropertiesResource":"mtr:properties_f2ec7453.json","positionDefinitionsResource":"mtr:definition_cfa409bd.json","flipTextureV":true}],"hasGangway1":false,"hasGangway2":true,"hasBarrier1":false,"hasBarrier2":false,"legacyRiderOffset":0.0,"bveSoundBaseResource":"e233","legacySpeedSoundBaseResource":"","legacySpeedSoundCount":1,"legacyUseAccelerationSoundsWhenCoasting":false,"legacyConstantPlaybackSpeed":false,"legacyDoorSoundBaseResource":"","legacyDoorCloseSoundTime":0.0},{"id":"mtr_custom_train_e2337_trailer","name":"E233-7000 Saikyo Line T","color":"2A8C56","transportMode":"TRAIN","length":20.0,"width":2.0,"bogie1Position":-6.8,"bogie2Position":6.8,"couplingPadding1":0.0,"couplingPadding2":0.0,"description":"Trailer Cab","wikipediaArticle":"E233_series","tags":[],"models":[{"modelResource":"mtr:e233/e233.bbmodel","textureResource":"mtr:e233/e233-7000.png","modelPropertiesResource":"mtr:properties_560821e.json","positionDefinitionsResource":"mtr:definition_9d6b8068.json","flipTextureV":true}],"bogie1Models":[{"modelResource":"mtr:e233/e233.bbmodel","textureResource":"mtr:e233/e233-0.png","modelPropertiesResource":"mtr:properties_e68bfd76.json","positionDefinitionsResource":"mtr:definition_df1d6e12.json","flipTextureV":true}],"bogie2Models":[{"modelResource":"mtr:e233/e233.bbmodel","textureResource":"mtr:e233/e233-0.png","modelPropertiesResource":"mtr:properties_4418aae3.json","positionDefinitionsResource":"mtr:definition_1f66e2e4.json","flipTextureV":true}],"hasGangway1":true,"hasGangway2":true,"hasBarrier1":false,"hasBarrier2":false,"legacyRiderOffset":0.0,"bveSoundBaseResource":"e233","legacySpeedSoundBaseResource":"","legacySpeedSoundCount":1,"legacyUseAccelerationSoundsWhenCoasting":false,"legacyConstantPlaybackSpeed":false,"legacyDoorSoundBaseResource":"","legacyDoorCloseSoundTime":0.0},{"id":"mtr_custom_train_e2337_pantograph_trailer","name":"E233-7000 Saikyo Line M'","color":"2A8C56","transportMode":"TRAIN","length":20.0,"width":2.0,"bogie1Position":-6.8,"bogie2Position":6.8,"couplingPadding1":0.0,"couplingPadding2":0.0,"description":"Double Pantograph Motor Trailer","wikipediaArticle":"E233_series","tags":[],"models":[{"modelResource":"mtr:e233/e233.bbmodel","textureResource":"mtr:e233/e233-7000.png","modelPropertiesResource":"mtr:properties_d194e815.json","positionDefinitionsResource":"mtr:definition_8d26e149.json","flipTextureV":true}],"bogie1Models":[{"modelResource":"mtr:e233/e233.bbmodel","textureResource":"mtr:e233/e233-0.png","modelPropertiesResource":"mtr:properties_4cb118a.json","positionDefinitionsResource":"mtr:definition_e8d1bebe.json","flipTextureV":true}],"bogie2Models":[{"modelResource":"mtr:e233/e233.bbmodel","textureResource":"mtr:e233/e233-0.png","modelPropertiesResource":"mtr:properties_9f50b0af.json","positionDefinitionsResource":"mtr:definition_69d2fcb3.json","flipTextureV":true}],"hasGangway1":true,"hasGangway2":true,"hasBarrier1":false,"hasBarrier2":false,"legacyRiderOffset":0.0,"bveSoundBaseResource":"e233","legacySpeedSoundBaseResource":"","legacySpeedSoundCount":1,"legacyUseAccelerationSoundsWhenCoasting":false,"legacyConstantPlaybackSpeed":false,"legacyDoorSoundBaseResource":"","legacyDoorCloseSoundTime":0.0},{"id":"mtr_custom_train_e2337_head_bqck","name":"E233-7000 Saikyo Line TC Back","color":"2A8C56","transportMode":"TRAIN","length":20.0,"width":2.0,"bogie1Position":-6.8,"bogie2Position":6.8,"couplingPadding1":0.0,"couplingPadding2":0.0,"description":"Trailer Cab","wikipediaArticle":"E233_series","tags":[],"models":[{"modelResource":"mtr:e233/e233.bbmodel","textureResource":"mtr:e233/e233-7000.png","modelPropertiesResource":"mtr:properties_99a139e4.json","positionDefinitionsResource":"mtr:definition_d3797ae6.json","flipTextureV":true}],"bogie1Models":[{"modelResource":"mtr:e233/e233.bbmodel","textureResource":"mtr:e233/e233-0.png","modelPropertiesResource":"mtr:properties_d9303360.json","positionDefinitionsResource":"mtr:definition_ad1bae01.json","flipTextureV":true}],"bogie2Models":[{"modelResource":"mtr:e233/e233.bbmodel","textureResource":"mtr:e233/e233-0.png","modelPropertiesResource":"mtr:properties_f2ec7453.json","positionDefinitionsResource":"mtr:definition_cfa409bd.json","flipTextureV":true}],"hasGangway1":true,"hasGangway2":false,"hasBarrier1":false,"hasBarrier2":false,"legacyRiderOffset":0.0,"bveSoundBaseResource":"e233","legacySpeedSoundBaseResource":"","legacySpeedSoundCount":1,"legacyUseAccelerationSoundsWhenCoasting":false,"legacyConstantPlaybackSpeed":false,"legacyDoorSoundBaseResource":"","legacyDoorCloseSoundTime":0.0},{"id":"mtr_custom_train_e2338_head","name":"E233-8000 Nambu Line TC Front","color":"FFFF00","transportMode":"TRAIN","length":20.0,"width":2.0,"bogie1Position":-6.8,"bogie2Position":6.8,"couplingPadding1":0.0,"couplingPadding2":0.0,"description":"Trailer Cab","wikipediaArticle":"E233_series","tags":[],"models":[{"modelResource":"mtr:e233/e233.bbmodel","textureResource":"mtr:e233/e233-8000.png","modelPropertiesResource":"mtr:properties_62a09756.json","positionDefinitionsResource":"mtr:definition_4d87d1d3.json","flipTextureV":true}],"bogie1Models":[{"modelResource":"mtr:e233/e233.bbmodel","textureResource":"mtr:e233/e233-0.png","modelPropertiesResource":"mtr:properties_cbfea844.json","positionDefinitionsResource":"mtr:definition_5b1c7883.json","flipTextureV":true}],"bogie2Models":[{"modelResource":"mtr:e233/e233.bbmodel","textureResource":"mtr:e233/e233-0.png","modelPropertiesResource":"mtr:properties_dc048c71.json","positionDefinitionsResource":"mtr:definition_14ec6651.json","flipTextureV":true}],"hasGangway1":false,"hasGangway2":true,"hasBarrier1":false,"hasBarrier2":false,"legacyRiderOffset":0.0,"bveSoundBaseResource":"e233","legacySpeedSoundBaseResource":"","legacySpeedSoundCount":1,"legacyUseAccelerationSoundsWhenCoasting":false,"legacyConstantPlaybackSpeed":false,"legacyDoorSoundBaseResource":"","legacyDoorCloseSoundTime":0.0},{"id":"mtr_custom_train_e2338_trailer","name":"E233-8000 Nambu Line T","color":"FFFF00","transportMode":"TRAIN","length":20.0,"width":2.0,"bogie1Position":-6.8,"bogie2Position":6.8,"couplingPadding1":0.0,"couplingPadding2":0.0,"description":"Trailer Cab","wikipediaArticle":"E233_series","tags":[],"models":[{"modelResource":"mtr:e233/e233.bbmodel","textureResource":"mtr:e233/e233-8000.png","modelPropertiesResource":"mtr:properties_1449c748.json","positionDefinitionsResource":"mtr:definition_9fde7b33.json","flipTextureV":true}],"bogie1Models":[{"modelResource":"mtr:e233/e233.bbmodel","textureResource":"mtr:e233/e233-0.png","modelPropertiesResource":"mtr:properties_6bc97280.json","positionDefinitionsResource":"mtr:definition_1744b75a.json","flipTextureV":true}],"bogie2Models":[{"modelResource":"mtr:e233/e233.bbmodel","textureResource":"mtr:e233/e233-0.png","modelPropertiesResource":"mtr:properties_46b7f7ab.json","positionDefinitionsResource":"mtr:definition_c8753713.json","flipTextureV":true}],"hasGangway1":true,"hasGangway2":true,"hasBarrier1":false,"hasBarrier2":false,"legacyRiderOffset":0.0,"bveSoundBaseResource":"e233","legacySpeedSoundBaseResource":"","legacySpeedSoundCount":1,"legacyUseAccelerationSoundsWhenCoasting":false,"legacyConstantPlaybackSpeed":false,"legacyDoorSoundBaseResource":"","legacyDoorCloseSoundTime":0.0},{"id":"mtr_custom_train_e2338_pantograph_trailer","name":"E233-8000 Nambu Line M'","color":"FFFF00","transportMode":"TRAIN","length":20.0,"width":2.0,"bogie1Position":-6.8,"bogie2Position":6.8,"couplingPadding1":0.0,"couplingPadding2":0.0,"description":"Double Pantograph Motor Trailer","wikipediaArticle":"E233_series","tags":[],"models":[{"modelResource":"mtr:e233/e233.bbmodel","textureResource":"mtr:e233/e233-8000.png","modelPropertiesResource":"mtr:properties_b2688f37.json","positionDefinitionsResource":"mtr:definition_f1a7a2db.json","flipTextureV":true}],"bogie1Models":[{"modelResource":"mtr:e233/e233.bbmodel","textureResource":"mtr:e233/e233-0.png","modelPropertiesResource":"mtr:properties_f454d4bb.json","positionDefinitionsResource":"mtr:definition_59ddfdfc.json","flipTextureV":true}],"bogie2Models":[{"modelResource":"mtr:e233/e233.bbmodel","textureResource":"mtr:e233/e233-0.png","modelPropertiesResource":"mtr:properties_4dc174dc.json","positionDefinitionsResource":"mtr:definition_e1e0a967.json","flipTextureV":true}],"hasGangway1":true,"hasGangway2":true,"hasBarrier1":false,"hasBarrier2":false,"legacyRiderOffset":0.0,"bveSoundBaseResource":"e233","legacySpeedSoundBaseResource":"","legacySpeedSoundCount":1,"legacyUseAccelerationSoundsWhenCoasting":false,"legacyConstantPlaybackSpeed":false,"legacyDoorSoundBaseResource":"","legacyDoorCloseSoundTime":0.0},{"id":"mtr_custom_train_e2338_head_bqck","name":"E233-8000 Nambu Line TC Back","color":"FFFF00","transportMode":"TRAIN","length":20.0,"width":2.0,"bogie1Position":-6.8,"bogie2Position":6.8,"couplingPadding1":0.0,"couplingPadding2":0.0,"description":"Trailer Cab","wikipediaArticle":"E233_series","tags":[],"models":[{"modelResource":"mtr:e233/e233.bbmodel","textureResource":"mtr:e233/e233-8000.png","modelPropertiesResource":"mtr:properties_ee56a72e.json","positionDefinitionsResource":"mtr:definition_f719090b.json","flipTextureV":true}],"bogie1Models":[{"modelResource":"mtr:e233/e233.bbmodel","textureResource":"mtr:e233/e233-0.png","modelPropertiesResource":"mtr:properties_cbfea844.json","positionDefinitionsResource":"mtr:definition_5b1c7883.json","flipTextureV":true}],"bogie2Models":[{"modelResource":"mtr:e233/e233.bbmodel","textureResource":"mtr:e233/e233-0.png","modelPropertiesResource":"mtr:properties_dc048c71.json","positionDefinitionsResource":"mtr:definition_14ec6651.json","flipTextureV":true}],"hasGangway1":true,"hasGangway2":false,"hasBarrier1":false,"hasBarrier2":false,"legacyRiderOffset":0.0,"bveSoundBaseResource":"e233","legacySpeedSoundBaseResource":"","legacySpeedSoundCount":1,"legacyUseAccelerationSoundsWhenCoasting":false,"legacyConstantPlaybackSpeed":false,"legacyDoorSoundBaseResource":"","legacyDoorCloseSoundTime":0.0}],"signs":[],"rails":[],"objects":[],"lifts":[]}
